scara_core/__init__.py
scara_core/clock.py
scara_core/errors.py
scara_core/protocols.py
scara_core/types.py
scara_core/utils.py
scara_core/validators.py
scara_index/__init__.py
scara_index/config.py
scara_index/filters.py
scara_index/qdrant_store.py
scara_rag/__init__.py
scara_rag/answerability.py
scara_rag/assembler.py
scara_rag/engine.py
scara_rag/errors.py
scara_rag/policies.py
scara_rag/prompts.py
scara_rag/rerankers.py
scara_rag/telemetry.py
scara_rag/types.py
scaraflow-0.1.8.dist-info/licenses/LICENSE
scaraflow-0.1.8.dist-info/METADATA
scaraflow-0.1.8.dist-info/WHEEL
scaraflow-0.1.8.dist-info/top_level.txt
scaraflow-0.1.8.dist-info/RECORD
