Metadata-Version: 2.4
Name: scaraflow
Version: 0.1.8
Summary: Retrieval-first, deterministic RAG infrastructure
Author: K. S. N. Ganesh
License: MIT
Project-URL: Homepage, https://github.com/ksnganesh/scaraflow
Project-URL: Repository, https://github.com/ksnganesh/scaraflow
Classifier: Development Status :: 3 - Alpha
Classifier: License :: OSI Approved :: MIT License
Classifier: Programming Language :: Python :: 3
Classifier: Programming Language :: Python :: 3.9
Classifier: Programming Language :: Python :: 3.10
Classifier: Programming Language :: Python :: 3.11
Classifier: Topic :: Scientific/Engineering :: Artificial Intelligence
Classifier: Topic :: Software Development :: Libraries
Requires-Python: >=3.9
License-File: LICENSE
Requires-Dist: qdrant-client>=1.7.0
Requires-Dist: numpy
Provides-Extra: bench
Requires-Dist: sentence-transformers; extra == "bench"
Requires-Dist: tqdm; extra == "bench"
Requires-Dist: pytest; extra == "bench"
Dynamic: license-file
